nas_201_api/__init__.py
nas_201_api/api_201.py
nas_201_api/api_utils.py
nas_bench_201-2.1.dist-info/LICENSE.md
nas_bench_201-2.1.dist-info/METADATA
nas_bench_201-2.1.dist-info/WHEEL
nas_bench_201-2.1.dist-info/top_level.txt
nas_bench_201-2.1.dist-info/RECORD
