Metadata-Version: 2.1
Name: nas-bench-201
Version: 2.1
Summary: API for NAS-Bench-201 (a benchmark for neural architecture search).
Home-page: https://github.com/D-X-Y/NAS-Bench-201
Author: Xuanyi Dong
Author-email: dongxuanyi888@gmail.com
License: MIT
Keywords: NAS Dataset API DeepLearning
Platform: UNKNOWN
Classifier: Programming Language :: Python
Classifier: Topic :: Database
Classifier: Topic :: Scientific/Engineering :: Artificial Intelligence
Classifier: License :: OSI Approved :: MIT License
